{
  "book_name": "2 Samuel",
  "chapter": 2,
  "verses": [
    {
      "book_name": "2 Samuel",
      "chapter": 2,
      "verse": 1,
      "text": "ויהי אחריכן וישאל דוד ביהוה לאמר האעלה באחת ערי יהודה ויאמר יהוה אליו עלה ויאמר דוד אנה אעלה ויאמר חברנה",
      "header": "",
      "footer": ""
    },
    {
      "book_name": "2 Samuel",
      "chapter": 2,
      "verse": 2,
      "text": "ויעל שם דוד וגם שתי נשיו אחינעם היזרעלית ואביגיל אשת נבל הכרמלי",
      "header": "",
      "footer": ""
    },
    {
      "book_name": "2 Samuel",
      "chapter": 2,
      "verse": 3,
      "text": "ואנשיו אשרעמו העלה דוד איש וביתו וישבו בערי חברון",
      "header": "",
      "footer": ""
    },
    {
      "book_name": "2 Samuel",
      "chapter": 2,
      "verse": 4,
      "text": "ויבאו אנשי יהודה וימשחושם אתדוד למלך עלבית יהודה ויגדו לדוד לאמר אנשי יביש גלעד אשר קברו אתשאול ס",
      "header": "",
      "footer": ""
    },
    {
      "book_name": "2 Samuel",
      "chapter": 2,
      "verse": 5,
      "text": "וישלח דוד מלאכים אלאנשי יביש גלעד ויאמר אליהם ברכים אתם ליהוה אשר עשיתם החסד הזה עםאדניכם עםשאול ותקברו אתו",
      "header": "",
      "footer": ""
    },
    {
      "book_name": "2 Samuel",
      "chapter": 2,
      "verse": 6,
      "text": "ועתה יעשיהוה עמכם חסד ואמת וגם אנכי אעשה אתכם הטובה הזאת אשר עשיתם הדבר הזה",
      "header": "",
      "footer": ""
    },
    {
      "book_name": "2 Samuel",
      "chapter": 2,
      "verse": 7,
      "text": "ועתה תחזקנה ידיכם והיו לבניחיל כימת אדניכם שאול וגםאתי משחו ביתיהודה למלך עליהם פ",
      "header": "",
      "footer": ""
    },
    {
      "book_name": "2 Samuel",
      "chapter": 2,
      "verse": 8,
      "text": "ואבנר בןנר שרצבא אשר לשאול לקח אתאיש בשת בןשאול ויעברהו מחנים",
      "header": "",
      "footer": ""
    },
    {
      "book_name": "2 Samuel",
      "chapter": 2,
      "verse": 9,
      "text": "וימלכהו אלהגלעד ואלהאשורי ואליזרעאל ועלאפרים ועלבנימן ועלישראל כלה פ",
      "header": "",
      "footer": ""
    },
    {
      "book_name": "2 Samuel",
      "chapter": 2,
      "verse": 10,
      "text": "בןארבעים שנה אישבשת בןשאול במלכו עלישראל ושתים שנים מלך אך בית יהודה היו אחרי דוד",
      "header": "",
      "footer": ""
    },
    {
      "book_name": "2 Samuel",
      "chapter": 2,
      "verse": 11,
      "text": "ויהי מספר הימים אשר היה דוד מלך בחברון עלבית יהודה שבע שנים וששה חדשים ס",
      "header": "",
      "footer": ""
    },
    {
      "book_name": "2 Samuel",
      "chapter": 2,
      "verse": 12,
      "text": "ויצא אבנר בןנר ועבדי אישבשת בןשאול ממחנים גבעונה",
      "header": "",
      "footer": ""
    },
    {
      "book_name": "2 Samuel",
      "chapter": 2,
      "verse": 13,
      "text": "ויואב בןצרויה ועבדי דוד יצאו ויפגשום עלברכת גבעון יחדו וישבו אלה עלהברכה מזה ואלה עלהברכה מזה",
      "header": "",
      "footer": ""
    },
    {
      "book_name": "2 Samuel",
      "chapter": 2,
      "verse": 14,
      "text": "ויאמר אבנר אליואב יקומו נא הנערים וישחקו לפנינו ויאמר יואב יקמו",
      "header": "",
      "footer": ""
    },
    {
      "book_name": "2 Samuel",
      "chapter": 2,
      "verse": 15,
      "text": "ויקמו ויעברו במספר שנים עשר לבנימן ולאיש בשת בןשאול ושנים עשר מעבדי דוד",
      "header": "",
      "footer": ""
    },
    {
      "book_name": "2 Samuel",
      "chapter": 2,
      "verse": 16,
      "text": "ויחזקו איש בראש רעהו וחרבו בצד רעהו ויפלו יחדו ויקרא למקום ההוא חלקת הצרים אשר בגבעון",
      "header": "",
      "footer": ""
    },
    {
      "book_name": "2 Samuel",
      "chapter": 2,
      "verse": 17,
      "text": "ותהי המלחמה קשה עדמאד ביום ההוא וינגף אבנר ואנשי ישראל לפני עבדי דוד",
      "header": "",
      "footer": ""
    },
    {
      "book_name": "2 Samuel",
      "chapter": 2,
      "verse": 18,
      "text": "ויהיושם שלשה בני צרויה יואב ואבישי ועשהאל ועשהאל קל ברגליו כאחד הצבים אשר בשדה",
      "header": "",
      "footer": ""
    },
    {
      "book_name": "2 Samuel",
      "chapter": 2,
      "verse": 19,
      "text": "וירדף עשהאל אחרי אבנר ולאנטה ללכת עלהימין ועלהשמאול מאחרי אבנר",
      "header": "",
      "footer": ""
    },
    {
      "book_name": "2 Samuel",
      "chapter": 2,
      "verse": 20,
      "text": "ויפן אבנר אחריו ויאמר האתה זה עשהאל ויאמר אנכי",
      "header": "",
      "footer": ""
    },
    {
      "book_name": "2 Samuel",
      "chapter": 2,
      "verse": 21,
      "text": "ויאמר לו אבנר נטה לך עלימינך או עלשמאלך ואחז לך אחד מהנערים וקחלך אתחלצתו ולאאבה עשהאל לסור מאחריו",
      "header": "",
      "footer": ""
    },
    {
      "book_name": "2 Samuel",
      "chapter": 2,
      "verse": 22,
      "text": "ויסף עוד אבנר לאמר אלעשהאל סור לך מאחרי למה אככה ארצה ואיך אשא פני אליואב אחיך",
      "header": "",
      "footer": ""
    },
    {
      "book_name": "2 Samuel",
      "chapter": 2,
      "verse": 23,
      "text": "וימאן לסור ויכהו אבנר באחרי החנית אלהחמש ותצא החנית מאחריו ויפלשם וימת תחתו ויהי כלהבא אלהמקום אשרנפל שם עשהאל וימת ויעמדו",
      "header": "",
      "footer": ""
    },
    {
      "book_name": "2 Samuel",
      "chapter": 2,
      "verse": 24,
      "text": "וירדפו יואב ואבישי אחרי אבנר והשמש באה והמה באו עדגבעת אמה אשר עלפניגיח דרך מדבר גבעון",
      "header": "",
      "footer": ""
    },
    {
      "book_name": "2 Samuel",
      "chapter": 2,
      "verse": 25,
      "text": "ויתקבצו בניבנימן אחרי אבנר ויהיו לאגדה אחת ויעמדו על ראשגבעה אחת",
      "header": "",
      "footer": ""
    },
    {
      "book_name": "2 Samuel",
      "chapter": 2,
      "verse": 26,
      "text": "ויקרא אבנר אליואב ויאמר הלנצח תאכל חרב הלוא ידעתה כימרה תהיה באחרונה ועדמתי לאתאמר לעם לשוב מאחרי אחיהם",
      "header": "",
      "footer": ""
    },
    {
      "book_name": "2 Samuel",
      "chapter": 2,
      "verse": 27,
      "text": "ויאמר יואב חי האלהים כי לולא דברת כי אז מהבקר נעלה העם איש מאחרי אחיו",
      "header": "",
      "footer": ""
    },
    {
      "book_name": "2 Samuel",
      "chapter": 2,
      "verse": 28,
      "text": "ויתקע יואב בשופר ויעמדו כלהעם ולאירדפו עוד אחרי ישראל ולאיספו עוד להלחם",
      "header": "",
      "footer": ""
    },
    {
      "book_name": "2 Samuel",
      "chapter": 2,
      "verse": 29,
      "text": "ואבנר ואנשיו הלכו בערבה כל הלילה ההוא ויעברו אתהירדן וילכו כלהבתרון ויבאו מחנים",
      "header": "",
      "footer": ""
    },
    {
      "book_name": "2 Samuel",
      "chapter": 2,
      "verse": 30,
      "text": "ויואב שב מאחרי אבנר ויקבץ אתכלהעם ויפקדו מעבדי דוד תשעהעשר איש ועשהאל",
      "header": "",
      "footer": ""
    },
    {
      "book_name": "2 Samuel",
      "chapter": 2,
      "verse": 31,
      "text": "ועבדי דוד הכו מבנימן ובאנשי אבנר שלשמאות וששים איש מתו",
      "header": "",
      "footer": ""
    },
    {
      "book_name": "2 Samuel",
      "chapter": 2,
      "verse": 32,
      "text": "וישאו אתעשהאל ויקברהו בקבר אביו אשר בית לחם וילכו כלהלילה יואב ואנשיו ויאר להם בחברון",
      "header": "",
      "footer": ""
    }
  ]
}