{
  "book_name": "2 Samuel",
  "chapter": 8,
  "verses": [
    {
      "book_name": "2 Samuel",
      "chapter": 8,
      "verse": 1,
      "text": "ויהי אחריכן ויך דוד אתפלשתים ויכניעם ויקח דוד אתמתג האמה מיד פלשתים",
      "header": "",
      "footer": ""
    },
    {
      "book_name": "2 Samuel",
      "chapter": 8,
      "verse": 2,
      "text": "ויך אתמואב וימדדם בחבל השכב אותם ארצה וימדד שניחבלים להמית ומלא החבל להחיות ותהי מואב לדוד לעבדים נשאי מנחה",
      "header": "",
      "footer": ""
    },
    {
      "book_name": "2 Samuel",
      "chapter": 8,
      "verse": 3,
      "text": "ויך דוד אתהדדעזר בןרחב מלך צובה בלכתו להשיב ידו בנהר",
      "header": "",
      "footer": ""
    },
    {
      "book_name": "2 Samuel",
      "chapter": 8,
      "verse": 4,
      "text": "וילכד דוד ממנו אלף ושבעמאות פרשים ועשרים אלף איש רגלי ויעקר דוד אתכלהרכב ויותר ממנו מאה רכב",
      "header": "",
      "footer": ""
    },
    {
      "book_name": "2 Samuel",
      "chapter": 8,
      "verse": 5,
      "text": "ותבא ארם דמשק לעזר להדדעזר מלך צובה ויך דוד בארם עשריםושנים אלף איש",
      "header": "",
      "footer": ""
    },
    {
      "book_name": "2 Samuel",
      "chapter": 8,
      "verse": 6,
      "text": "וישם דוד נצבים בארם דמשק ותהי ארם לדוד לעבדים נושאי מנחה וישע יהוה אתדוד בכל אשר הלך",
      "header": "",
      "footer": ""
    },
    {
      "book_name": "2 Samuel",
      "chapter": 8,
      "verse": 7,
      "text": "ויקח דוד את שלטי הזהב אשר היו אל עבדי הדדעזר ויביאם ירושלם",
      "header": "",
      "footer": ""
    },
    {
      "book_name": "2 Samuel",
      "chapter": 8,
      "verse": 8,
      "text": "ומבטח ומברתי ערי הדדעזר לקח המלך דוד נחשת הרבה מאד ס",
      "header": "",
      "footer": ""
    },
    {
      "book_name": "2 Samuel",
      "chapter": 8,
      "verse": 9,
      "text": "וישמע תעי מלך חמת כי הכה דוד את כלחיל הדדעזר",
      "header": "",
      "footer": ""
    },
    {
      "book_name": "2 Samuel",
      "chapter": 8,
      "verse": 10,
      "text": "וישלח תעי אתיורםבנו אלהמלךדוד לשאללו לשלום ולברכו על אשר נלחם בהדדעזר ויכהו כיאיש מלחמות תעי היה הדדעזר ובידו היו כליכסף וכליזהב וכלי נחשת",
      "header": "",
      "footer": ""
    },
    {
      "book_name": "2 Samuel",
      "chapter": 8,
      "verse": 11,
      "text": "גםאתם הקדיש המלך דוד ליהוה עםהכסף והזהב אשר הקדיש מכלהגוים אשר כבש",
      "header": "",
      "footer": ""
    },
    {
      "book_name": "2 Samuel",
      "chapter": 8,
      "verse": 12,
      "text": "מארם וממואב ומבני עמון ומפלשתים ומעמלק ומשלל הדדעזר בןרחב מלך צובה",
      "header": "",
      "footer": ""
    },
    {
      "book_name": "2 Samuel",
      "chapter": 8,
      "verse": 13,
      "text": "ויעש דוד שם בשבו מהכותו אתארם בגיאמלח שמונה עשר אלף",
      "header": "",
      "footer": ""
    },
    {
      "book_name": "2 Samuel",
      "chapter": 8,
      "verse": 14,
      "text": "וישם באדום נצבים בכלאדום שם נצבים ויהי כלאדום עבדים לדוד ויושע יהוה אתדוד בכל אשר הלך",
      "header": "",
      "footer": ""
    },
    {
      "book_name": "2 Samuel",
      "chapter": 8,
      "verse": 15,
      "text": "וימלך דוד עלכלישראל ויהי דוד עשה משפט וצדקה לכלעמו",
      "header": "",
      "footer": ""
    },
    {
      "book_name": "2 Samuel",
      "chapter": 8,
      "verse": 16,
      "text": "ויואב בןצרויה עלהצבא ויהושפט בןאחילוד מזכיר",
      "header": "",
      "footer": ""
    },
    {
      "book_name": "2 Samuel",
      "chapter": 8,
      "verse": 17,
      "text": "וצדוק בןאחיטוב ואחימלך בןאביתר כהנים ושריה סופר",
      "header": "",
      "footer": ""
    },
    {
      "book_name": "2 Samuel",
      "chapter": 8,
      "verse": 18,
      "text": "ובניהו בןיהוידע והכרתי והפלתי ובני דוד כהנים היו פ",
      "header": "",
      "footer": ""
    }
  ]
}