{
  "book_name": "Hosea",
  "chapter": 9,
  "verses": [
    {
      "book_name": "Hosea",
      "chapter": 9,
      "verse": 1,
      "text": "אלתשמח ישראל אלגיל כעמים כי זנית מעל אלהיך אהבת אתנן על כלגרנות דגן",
      "header": "",
      "footer": ""
    },
    {
      "book_name": "Hosea",
      "chapter": 9,
      "verse": 2,
      "text": "גרן ויקב לא ירעם ותירוש יכחש בה",
      "header": "",
      "footer": ""
    },
    {
      "book_name": "Hosea",
      "chapter": 9,
      "verse": 3,
      "text": "לא ישבו בארץ יהוה ושב אפרים מצרים ובאשור טמא יאכלו",
      "header": "",
      "footer": ""
    },
    {
      "book_name": "Hosea",
      "chapter": 9,
      "verse": 4,
      "text": "לאיסכו ליהוה יין ולא יערבולו זבחיהם כלחם אונים להם כלאכליו יטמאו כילחמם לנפשם לא יבוא בית יהוה",
      "header": "",
      "footer": ""
    },
    {
      "book_name": "Hosea",
      "chapter": 9,
      "verse": 5,
      "text": "מהתעשו ליום מועד וליום חגיהוה",
      "header": "",
      "footer": ""
    },
    {
      "book_name": "Hosea",
      "chapter": 9,
      "verse": 6,
      "text": "כיהנה הלכו משד מצרים תקבצם מף תקברם מחמד לכספם קמוש יירשם חוח באהליהם",
      "header": "",
      "footer": ""
    },
    {
      "book_name": "Hosea",
      "chapter": 9,
      "verse": 7,
      "text": "באו ימי הפקדה באו ימי השלם ידעו ישראל אויל הנביא משגע איש הרוח על רב עונך ורבה משטמה",
      "header": "",
      "footer": ""
    },
    {
      "book_name": "Hosea",
      "chapter": 9,
      "verse": 8,
      "text": "צפה אפרים עםאלהי נביא פח יקוש עלכלדרכיו משטמה בבית אלהיו",
      "header": "",
      "footer": ""
    },
    {
      "book_name": "Hosea",
      "chapter": 9,
      "verse": 9,
      "text": "העמיקושחתו כימי הגבעה יזכור עונם יפקוד חטאותם ס",
      "header": "",
      "footer": ""
    },
    {
      "book_name": "Hosea",
      "chapter": 9,
      "verse": 10,
      "text": "כענבים במדבר מצאתי ישראל כבכורה בתאנה בראשיתה ראיתי אבותיכם המה באו בעלפעור וינזרו לבשת ויהיו שקוצים כאהבם",
      "header": "",
      "footer": ""
    },
    {
      "book_name": "Hosea",
      "chapter": 9,
      "verse": 11,
      "text": "אפרים כעוף יתעופף כבודם מלדה ומבטן ומהריון",
      "header": "",
      "footer": ""
    },
    {
      "book_name": "Hosea",
      "chapter": 9,
      "verse": 12,
      "text": "כי אםיגדלו אתבניהם ושכלתים מאדם כיגםאוי להם בשורי מהם",
      "header": "",
      "footer": ""
    },
    {
      "book_name": "Hosea",
      "chapter": 9,
      "verse": 13,
      "text": "אפרים כאשרראיתי לצור שתולה בנוה ואפרים להוציא אלהרג בניו",
      "header": "",
      "footer": ""
    },
    {
      "book_name": "Hosea",
      "chapter": 9,
      "verse": 14,
      "text": "תןלהם יהוה מהתתן תןלהם רחם משכיל ושדים צמקים",
      "header": "",
      "footer": ""
    },
    {
      "book_name": "Hosea",
      "chapter": 9,
      "verse": 15,
      "text": "כלרעתם בגלגל כישם שנאתים על רע מעלליהם מביתי אגרשם לא אוסף אהבתם כלשריהם סררים",
      "header": "",
      "footer": ""
    },
    {
      "book_name": "Hosea",
      "chapter": 9,
      "verse": 16,
      "text": "הכה אפרים שרשם יבש פרי בלייעשון גם כי ילדון והמתי מחמדי בטנם ס",
      "header": "",
      "footer": ""
    },
    {
      "book_name": "Hosea",
      "chapter": 9,
      "verse": 17,
      "text": "ימאסם אלהי כי לא שמעו לו ויהיו נדדים בגוים ס",
      "header": "",
      "footer": ""
    }
  ]
}