{
  "book_name": "Genesis",
  "chapter": 29,
  "verses": [
    {
      "book_name": "Genesis",
      "chapter": 29,
      "verse": 1,
      "text": "וישא יעקב רגליו וילך ארצה בניקדם",
      "header": "",
      "footer": ""
    },
    {
      "book_name": "Genesis",
      "chapter": 29,
      "verse": 2,
      "text": "וירא והנה באר בשדה והנהשם שלשה עדריצאן רבצים עליה כי מןהבאר ההוא ישקו העדרים והאבן גדלה עלפי הבאר",
      "header": "",
      "footer": ""
    },
    {
      "book_name": "Genesis",
      "chapter": 29,
      "verse": 3,
      "text": "ונאספושמה כלהעדרים וגללו אתהאבן מעל פי הבאר והשקו אתהצאן והשיבו אתהאבן עלפי הבאר למקמה",
      "header": "",
      "footer": ""
    },
    {
      "book_name": "Genesis",
      "chapter": 29,
      "verse": 4,
      "text": "ויאמר להם יעקב אחי מאין אתם ויאמרו מחרן אנחנו",
      "header": "",
      "footer": ""
    },
    {
      "book_name": "Genesis",
      "chapter": 29,
      "verse": 5,
      "text": "ויאמר להם הידעתם אתלבן בןנחור ויאמרו ידענו",
      "header": "",
      "footer": ""
    },
    {
      "book_name": "Genesis",
      "chapter": 29,
      "verse": 6,
      "text": "ויאמר להם השלום לו ויאמרו שלום והנה רחל בתו באה עםהצאן",
      "header": "",
      "footer": ""
    },
    {
      "book_name": "Genesis",
      "chapter": 29,
      "verse": 7,
      "text": "ויאמר הן עוד היום גדול לאעת האסף המקנה השקו הצאן ולכו רעו",
      "header": "",
      "footer": ""
    },
    {
      "book_name": "Genesis",
      "chapter": 29,
      "verse": 8,
      "text": "ויאמרו לא נוכל עד אשר יאספו כלהעדרים וגללו אתהאבן מעל פי הבאר והשקינו הצאן",
      "header": "",
      "footer": ""
    },
    {
      "book_name": "Genesis",
      "chapter": 29,
      "verse": 9,
      "text": "עודנו מדבר עמם ורחל באה עםהצאן אשר לאביה כי רעה הוא",
      "header": "",
      "footer": ""
    },
    {
      "book_name": "Genesis",
      "chapter": 29,
      "verse": 10,
      "text": "ויהי כאשר ראה יעקב אתרחל בתלבן אחי אמו ואתצאן לבן אחי אמו ויגש יעקב ויגל אתהאבן מעל פי הבאר וישק אתצאן לבן אחי אמו",
      "header": "",
      "footer": ""
    },
    {
      "book_name": "Genesis",
      "chapter": 29,
      "verse": 11,
      "text": "וישק יעקב לרחל וישא אתקלו ויבך",
      "header": "",
      "footer": ""
    },
    {
      "book_name": "Genesis",
      "chapter": 29,
      "verse": 12,
      "text": "ויגד יעקב לרחל כי אחי אביה הוא וכי בןרבקה הוא ותרץ ותגד לאביה",
      "header": "",
      "footer": ""
    },
    {
      "book_name": "Genesis",
      "chapter": 29,
      "verse": 13,
      "text": "ויהי כשמע לבן אתשמע יעקב בןאחתו וירץ לקראתו ויחבקלו וינשקלו ויביאהו אלביתו ויספר ללבן את כלהדברים האלה",
      "header": "",
      "footer": ""
    },
    {
      "book_name": "Genesis",
      "chapter": 29,
      "verse": 14,
      "text": "ויאמר לו לבן אך עצמי ובשרי אתה וישב עמו חדש ימים",
      "header": "",
      "footer": ""
    },
    {
      "book_name": "Genesis",
      "chapter": 29,
      "verse": 15,
      "text": "ויאמר לבן ליעקב הכיאחי אתה ועבדתני חנם הגידה לי מהמשכרתך",
      "header": "",
      "footer": ""
    },
    {
      "book_name": "Genesis",
      "chapter": 29,
      "verse": 16,
      "text": "וללבן שתי בנות שם הגדלה לאה ושם הקטנה רחל",
      "header": "",
      "footer": ""
    },
    {
      "book_name": "Genesis",
      "chapter": 29,
      "verse": 17,
      "text": "ועיני לאה רכות ורחל היתה יפתתאר ויפת מראה",
      "header": "",
      "footer": ""
    },
    {
      "book_name": "Genesis",
      "chapter": 29,
      "verse": 18,
      "text": "ויאהב יעקב אתרחל ויאמר אעבדך שבע שנים ברחל בתך הקטנה",
      "header": "",
      "footer": ""
    },
    {
      "book_name": "Genesis",
      "chapter": 29,
      "verse": 19,
      "text": "ויאמר לבן טוב תתי אתה לך מתתי אתה לאיש אחר שבה עמדי",
      "header": "",
      "footer": ""
    },
    {
      "book_name": "Genesis",
      "chapter": 29,
      "verse": 20,
      "text": "ויעבד יעקב ברחל שבע שנים ויהיו בעיניו כימים אחדים באהבתו אתה",
      "header": "",
      "footer": ""
    },
    {
      "book_name": "Genesis",
      "chapter": 29,
      "verse": 21,
      "text": "ויאמר יעקב אללבן הבה אתאשתי כי מלאו ימי ואבואה אליה",
      "header": "",
      "footer": ""
    },
    {
      "book_name": "Genesis",
      "chapter": 29,
      "verse": 22,
      "text": "ויאסף לבן אתכלאנשי המקום ויעש משתה",
      "header": "",
      "footer": ""
    },
    {
      "book_name": "Genesis",
      "chapter": 29,
      "verse": 23,
      "text": "ויהי בערב ויקח אתלאה בתו ויבא אתה אליו ויבא אליה",
      "header": "",
      "footer": ""
    },
    {
      "book_name": "Genesis",
      "chapter": 29,
      "verse": 24,
      "text": "ויתן לבן לה אתזלפה שפחתו ללאה בתו שפחה",
      "header": "",
      "footer": ""
    },
    {
      "book_name": "Genesis",
      "chapter": 29,
      "verse": 25,
      "text": "ויהי בבקר והנההוא לאה ויאמר אללבן מהזאת עשית לי הלא ברחל עבדתי עמך ולמה רמיתני",
      "header": "",
      "footer": ""
    },
    {
      "book_name": "Genesis",
      "chapter": 29,
      "verse": 26,
      "text": "ויאמר לבן לאיעשה כן במקומנו לתת הצעירה לפני הבכירה",
      "header": "",
      "footer": ""
    },
    {
      "book_name": "Genesis",
      "chapter": 29,
      "verse": 27,
      "text": "מלא שבע זאת ונתנה לך גםאתזאת בעבדה אשר תעבד עמדי עוד שבעשנים אחרות",
      "header": "",
      "footer": ""
    },
    {
      "book_name": "Genesis",
      "chapter": 29,
      "verse": 28,
      "text": "ויעש יעקב כן וימלא שבע זאת ויתןלו אתרחל בתו לו לאשה",
      "header": "",
      "footer": ""
    },
    {
      "book_name": "Genesis",
      "chapter": 29,
      "verse": 29,
      "text": "ויתן לבן לרחל בתו אתבלהה שפחתו לה לשפחה",
      "header": "",
      "footer": ""
    },
    {
      "book_name": "Genesis",
      "chapter": 29,
      "verse": 30,
      "text": "ויבא גם אלרחל ויאהב גםאתרחל מלאה ויעבד עמו עוד שבעשנים אחרות",
      "header": "",
      "footer": ""
    },
    {
      "book_name": "Genesis",
      "chapter": 29,
      "verse": 31,
      "text": "וירא יהוה כישנואה לאה ויפתח אתרחמה ורחל עקרה",
      "header": "",
      "footer": ""
    },
    {
      "book_name": "Genesis",
      "chapter": 29,
      "verse": 32,
      "text": "ותהר לאה ותלד בן ותקרא שמו ראובן כי אמרה כיראה יהוה בעניי כי עתה יאהבני אישי",
      "header": "",
      "footer": ""
    },
    {
      "book_name": "Genesis",
      "chapter": 29,
      "verse": 33,
      "text": "ותהר עוד ותלד בן ותאמר כישמע יהוה כישנואה אנכי ויתןלי גםאתזה ותקרא שמו שמעון",
      "header": "",
      "footer": ""
    },
    {
      "book_name": "Genesis",
      "chapter": 29,
      "verse": 34,
      "text": "ותהר עוד ותלד בן ותאמר עתה הפעם ילוה אישי אלי כיילדתי לו שלשה בנים עלכן קראשמו לוי",
      "header": "",
      "footer": ""
    },
    {
      "book_name": "Genesis",
      "chapter": 29,
      "verse": 35,
      "text": "ותהר עוד ותלד בן ותאמר הפעם אודה אתיהוה עלכן קראה שמו יהודה ותעמד מלדת",
      "header": "",
      "footer": ""
    }
  ]
}