{
  "book_name": "Genesis",
  "chapter": 40,
  "verses": [
    {
      "book_name": "Genesis",
      "chapter": 40,
      "verse": 1,
      "text": "ויהי אחר הדברים האלה חטאו משקה מלךמצרים והאפה לאדניהם למלך מצרים",
      "header": "",
      "footer": ""
    },
    {
      "book_name": "Genesis",
      "chapter": 40,
      "verse": 2,
      "text": "ויקצף פרעה על שני סריסיו על שר המשקים ועל שר האופים",
      "header": "",
      "footer": ""
    },
    {
      "book_name": "Genesis",
      "chapter": 40,
      "verse": 3,
      "text": "ויתן אתם במשמר בית שר הטבחים אלבית הסהר מקום אשר יוסף אסור שם",
      "header": "",
      "footer": ""
    },
    {
      "book_name": "Genesis",
      "chapter": 40,
      "verse": 4,
      "text": "ויפקד שר הטבחים אתיוסף אתם וישרת אתם ויהיו ימים במשמר",
      "header": "",
      "footer": ""
    },
    {
      "book_name": "Genesis",
      "chapter": 40,
      "verse": 5,
      "text": "ויחלמו חלום שניהם איש חלמו בלילה אחד איש כפתרון חלמו המשקה והאפה אשר למלך מצרים אשר אסורים בבית הסהר",
      "header": "",
      "footer": ""
    },
    {
      "book_name": "Genesis",
      "chapter": 40,
      "verse": 6,
      "text": "ויבא אליהם יוסף בבקר וירא אתם והנם זעפים",
      "header": "",
      "footer": ""
    },
    {
      "book_name": "Genesis",
      "chapter": 40,
      "verse": 7,
      "text": "וישאל אתסריסי פרעה אשר אתו במשמר בית אדניו לאמר מדוע פניכם רעים היום",
      "header": "",
      "footer": ""
    },
    {
      "book_name": "Genesis",
      "chapter": 40,
      "verse": 8,
      "text": "ויאמרו אליו חלום חלמנו ופתר אין אתו ויאמר אלהם יוסף הלוא לאלהים פתרנים ספרונא לי",
      "header": "",
      "footer": ""
    },
    {
      "book_name": "Genesis",
      "chapter": 40,
      "verse": 9,
      "text": "ויספר שרהמשקים אתחלמו ליוסף ויאמר לו בחלומי והנהגפן לפני",
      "header": "",
      "footer": ""
    },
    {
      "book_name": "Genesis",
      "chapter": 40,
      "verse": 10,
      "text": "ובגפן שלשה שריגם והיא כפרחת עלתה נצה הבשילו אשכלתיה ענבים",
      "header": "",
      "footer": ""
    },
    {
      "book_name": "Genesis",
      "chapter": 40,
      "verse": 11,
      "text": "וכוס פרעה בידי ואקח אתהענבים ואשחט אתם אלכוס פרעה ואתן אתהכוס עלכף פרעה",
      "header": "",
      "footer": ""
    },
    {
      "book_name": "Genesis",
      "chapter": 40,
      "verse": 12,
      "text": "ויאמר לו יוסף זה פתרנו שלשת השרגים שלשת ימים הם",
      "header": "",
      "footer": ""
    },
    {
      "book_name": "Genesis",
      "chapter": 40,
      "verse": 13,
      "text": "בעוד שלשת ימים ישא פרעה אתראשך והשיבך עלכנך ונתת כוספרעה בידו כמשפט הראשון אשר היית משקהו",
      "header": "",
      "footer": ""
    },
    {
      "book_name": "Genesis",
      "chapter": 40,
      "verse": 14,
      "text": "כי אםזכרתני אתך כאשר ייטב לך ועשיתנא עמדי חסד והזכרתני אלפרעה והוצאתני מןהבית הזה",
      "header": "",
      "footer": ""
    },
    {
      "book_name": "Genesis",
      "chapter": 40,
      "verse": 15,
      "text": "כיגנב גנבתי מארץ העברים וגםפה לאעשיתי מאומה כישמו אתי בבור",
      "header": "",
      "footer": ""
    },
    {
      "book_name": "Genesis",
      "chapter": 40,
      "verse": 16,
      "text": "וירא שרהאפים כי טוב פתר ויאמר אליוסף אףאני בחלומי והנה שלשה סלי חרי עלראשי",
      "header": "",
      "footer": ""
    },
    {
      "book_name": "Genesis",
      "chapter": 40,
      "verse": 17,
      "text": "ובסל העליון מכל מאכל פרעה מעשה אפה והעוף אכל אתם מןהסל מעל ראשי",
      "header": "",
      "footer": ""
    },
    {
      "book_name": "Genesis",
      "chapter": 40,
      "verse": 18,
      "text": "ויען יוסף ויאמר זה פתרנו שלשת הסלים שלשת ימים הם",
      "header": "",
      "footer": ""
    },
    {
      "book_name": "Genesis",
      "chapter": 40,
      "verse": 19,
      "text": "בעוד שלשת ימים ישא פרעה אתראשך מעליך ותלה אותך עלעץ ואכל העוף אתבשרך מעליך",
      "header": "",
      "footer": ""
    },
    {
      "book_name": "Genesis",
      "chapter": 40,
      "verse": 20,
      "text": "ויהי ביום השלישי יום הלדת אתפרעה ויעש משתה לכלעבדיו וישא אתראש שר המשקים ואתראש שר האפים בתוך עבדיו",
      "header": "",
      "footer": ""
    },
    {
      "book_name": "Genesis",
      "chapter": 40,
      "verse": 21,
      "text": "וישב אתשר המשקים עלמשקהו ויתן הכוס עלכף פרעה",
      "header": "",
      "footer": ""
    },
    {
      "book_name": "Genesis",
      "chapter": 40,
      "verse": 22,
      "text": "ואת שר האפים תלה כאשר פתר להם יוסף",
      "header": "",
      "footer": ""
    },
    {
      "book_name": "Genesis",
      "chapter": 40,
      "verse": 23,
      "text": "ולאזכר שרהמשקים אתיוסף וישכחהו פ",
      "header": "",
      "footer": ""
    }
  ]
}