{
  "book_name": "Ezekiel",
  "chapter": 20,
  "verses": [
    {
      "book_name": "Ezekiel",
      "chapter": 20,
      "verse": 1,
      "text": "ויהי בשנה השביעית בחמשי בעשור לחדש באו אנשים מזקני ישראל לדרש אתיהוה וישבו לפני ס",
      "header": "",
      "footer": ""
    },
    {
      "book_name": "Ezekiel",
      "chapter": 20,
      "verse": 2,
      "text": "ויהי דבריהוה אלי לאמר",
      "header": "",
      "footer": ""
    },
    {
      "book_name": "Ezekiel",
      "chapter": 20,
      "verse": 3,
      "text": "בןאדם דבר אתזקני ישראל ואמרת אלהם כה אמר אדני יהוה הלדרש אתי אתם באים חיאני אםאדרש לכם נאם אדני יהוה",
      "header": "",
      "footer": ""
    },
    {
      "book_name": "Ezekiel",
      "chapter": 20,
      "verse": 4,
      "text": "התשפט אתם התשפוט בןאדם אתתועבת אבותם הודיעם",
      "header": "",
      "footer": ""
    },
    {
      "book_name": "Ezekiel",
      "chapter": 20,
      "verse": 5,
      "text": "ואמרת אליהם כהאמר אדני יהוה ביום בחרי בישראל ואשא ידי לזרע בית יעקב ואודע להם בארץ מצרים ואשא ידי להם לאמר אני יהוה אלהיכם",
      "header": "",
      "footer": ""
    },
    {
      "book_name": "Ezekiel",
      "chapter": 20,
      "verse": 6,
      "text": "ביום ההוא נשאתי ידי להם להוציאם מארץ מצרים אלארץ אשרתרתי להם זבת חלב ודבש צבי היא לכלהארצות",
      "header": "",
      "footer": ""
    },
    {
      "book_name": "Ezekiel",
      "chapter": 20,
      "verse": 7,
      "text": "ואמר אלהם איש שקוצי עיניו השליכו ובגלולי מצרים אלתטמאו אני יהוה אלהיכם",
      "header": "",
      "footer": ""
    },
    {
      "book_name": "Ezekiel",
      "chapter": 20,
      "verse": 8,
      "text": "וימרובי ולא אבו לשמע אלי איש אתשקוצי עיניהם לא השליכו ואתגלולי מצרים לא עזבו ואמר לשפך חמתי עליהם לכלות אפי בהם בתוך ארץ מצרים",
      "header": "",
      "footer": ""
    },
    {
      "book_name": "Ezekiel",
      "chapter": 20,
      "verse": 9,
      "text": "ואעש למען שמי לבלתי החל לעיני הגוים אשרהמה בתוכם אשר נודעתי אליהם לעיניהם להוציאם מארץ מצרים",
      "header": "",
      "footer": ""
    },
    {
      "book_name": "Ezekiel",
      "chapter": 20,
      "verse": 10,
      "text": "ואוציאם מארץ מצרים ואבאם אלהמדבר",
      "header": "",
      "footer": ""
    },
    {
      "book_name": "Ezekiel",
      "chapter": 20,
      "verse": 11,
      "text": "ואתן להם אתחקותי ואתמשפטי הודעתי אותם אשר יעשה אותם האדם וחי בהם",
      "header": "",
      "footer": ""
    },
    {
      "book_name": "Ezekiel",
      "chapter": 20,
      "verse": 12,
      "text": "וגם אתשבתותי נתתי להם להיות לאות ביני וביניהם לדעת כי אני יהוה מקדשם",
      "header": "",
      "footer": ""
    },
    {
      "book_name": "Ezekiel",
      "chapter": 20,
      "verse": 13,
      "text": "וימרובי ביתישראל במדבר בחקותי לאהלכו ואתמשפטי מאסו אשר יעשה אתם האדם וחי בהם ואתשבתתי חללו מאד ואמר לשפך חמתי עליהם במדבר לכלותם",
      "header": "",
      "footer": ""
    },
    {
      "book_name": "Ezekiel",
      "chapter": 20,
      "verse": 14,
      "text": "ואעשה למען שמי לבלתי החל לעיני הגוים אשר הוצאתים לעיניהם",
      "header": "",
      "footer": ""
    },
    {
      "book_name": "Ezekiel",
      "chapter": 20,
      "verse": 15,
      "text": "וגםאני נשאתי ידי להם במדבר לבלתי הביא אותם אלהארץ אשרנתתי זבת חלב ודבש צבי היא לכלהארצות",
      "header": "",
      "footer": ""
    },
    {
      "book_name": "Ezekiel",
      "chapter": 20,
      "verse": 16,
      "text": "יען במשפטי מאסו ואתחקותי לאהלכו בהם ואתשבתותי חללו כי אחרי גלוליהם לבם הלך",
      "header": "",
      "footer": ""
    },
    {
      "book_name": "Ezekiel",
      "chapter": 20,
      "verse": 17,
      "text": "ותחס עיני עליהם משחתם ולאעשיתי אותם כלה במדבר",
      "header": "",
      "footer": ""
    },
    {
      "book_name": "Ezekiel",
      "chapter": 20,
      "verse": 18,
      "text": "ואמר אלבניהם במדבר בחוקי אבותיכם אלתלכו ואתמשפטיהם אלתשמרו ובגלוליהם אלתטמאו",
      "header": "",
      "footer": ""
    },
    {
      "book_name": "Ezekiel",
      "chapter": 20,
      "verse": 19,
      "text": "אני יהוה אלהיכם בחקותי לכו ואתמשפטי שמרו ועשו אותם",
      "header": "",
      "footer": ""
    },
    {
      "book_name": "Ezekiel",
      "chapter": 20,
      "verse": 20,
      "text": "ואתשבתותי קדשו והיו לאות ביני וביניכם לדעת כי אני יהוה אלהיכם",
      "header": "",
      "footer": ""
    },
    {
      "book_name": "Ezekiel",
      "chapter": 20,
      "verse": 21,
      "text": "וימרובי הבנים בחקותי לאהלכו ואתמשפטי לאשמרו לעשות אותם אשר יעשה אותם האדם וחי בהם אתשבתותי חללו ואמר לשפך חמתי עליהם לכלות אפי בם במדבר",
      "header": "",
      "footer": ""
    },
    {
      "book_name": "Ezekiel",
      "chapter": 20,
      "verse": 22,
      "text": "והשבתי אתידי ואעש למען שמי לבלתי החל לעיני הגוים אשרהוצאתי אותם לעיניהם",
      "header": "",
      "footer": ""
    },
    {
      "book_name": "Ezekiel",
      "chapter": 20,
      "verse": 23,
      "text": "גםאני נשאתי אתידי להם במדבר להפיץ אתם בגוים ולזרות אותם בארצות",
      "header": "",
      "footer": ""
    },
    {
      "book_name": "Ezekiel",
      "chapter": 20,
      "verse": 24,
      "text": "יען משפטי לאעשו וחקותי מאסו ואתשבתותי חללו ואחרי גלולי אבותם היו עיניהם",
      "header": "",
      "footer": ""
    },
    {
      "book_name": "Ezekiel",
      "chapter": 20,
      "verse": 25,
      "text": "וגםאני נתתי להם חקים לא טובים ומשפטים לא יחיו בהם",
      "header": "",
      "footer": ""
    },
    {
      "book_name": "Ezekiel",
      "chapter": 20,
      "verse": 26,
      "text": "ואטמא אותם במתנותם בהעביר כלפטר רחם למען אשמם למען אשר ידעו אשר אני יהוה ס",
      "header": "",
      "footer": ""
    },
    {
      "book_name": "Ezekiel",
      "chapter": 20,
      "verse": 27,
      "text": "לכן דבר אלבית ישראל בןאדם ואמרת אליהם כה אמר אדני יהוה עוד זאת גדפו אותי אבותיכם במעלם בי מעל",
      "header": "",
      "footer": ""
    },
    {
      "book_name": "Ezekiel",
      "chapter": 20,
      "verse": 28,
      "text": "ואביאם אלהארץ אשר נשאתי אתידי לתת אותה להם ויראו כלגבעה רמה וכלעץ עבת ויזבחושם אתזבחיהם ויתנושם כעס קרבנם וישימו שם ריח ניחוחיהם ויסיכו שם אתנסכיהם",
      "header": "",
      "footer": ""
    },
    {
      "book_name": "Ezekiel",
      "chapter": 20,
      "verse": 29,
      "text": "ואמר אלהם מה הבמה אשראתם הבאים שם ויקרא שמה במה עד היום הזה",
      "header": "",
      "footer": ""
    },
    {
      "book_name": "Ezekiel",
      "chapter": 20,
      "verse": 30,
      "text": "לכן אמר אלבית ישראל כה אמר אדני יהוה הבדרך אבותיכם אתם נטמאים ואחרי שקוציהם אתם זנים",
      "header": "",
      "footer": ""
    },
    {
      "book_name": "Ezekiel",
      "chapter": 20,
      "verse": 31,
      "text": "ובשאת מתנתיכם בהעביר בניכם באש אתם נטמאים לכלגלוליכם עדהיום ואני אדרש לכם בית ישראל חיאני נאם אדני יהוה אםאדרש לכם",
      "header": "",
      "footer": ""
    },
    {
      "book_name": "Ezekiel",
      "chapter": 20,
      "verse": 32,
      "text": "והעלה עלרוחכם היו לא תהיה אשר אתם אמרים נהיה כגוים כמשפחות הארצות לשרת עץ ואבן",
      "header": "",
      "footer": ""
    },
    {
      "book_name": "Ezekiel",
      "chapter": 20,
      "verse": 33,
      "text": "חיאני נאם אדני יהוה אםלא ביד חזקה ובזרוע נטויה ובחמה שפוכה אמלוך עליכם",
      "header": "",
      "footer": ""
    },
    {
      "book_name": "Ezekiel",
      "chapter": 20,
      "verse": 34,
      "text": "והוצאתי אתכם מןהעמים וקבצתי אתכם מןהארצות אשר נפוצתם בם ביד חזקה ובזרוע נטויה ובחמה שפוכה",
      "header": "",
      "footer": ""
    },
    {
      "book_name": "Ezekiel",
      "chapter": 20,
      "verse": 35,
      "text": "והבאתי אתכם אלמדבר העמים ונשפטתי אתכם שם פנים אלפנים",
      "header": "",
      "footer": ""
    },
    {
      "book_name": "Ezekiel",
      "chapter": 20,
      "verse": 36,
      "text": "כאשר נשפטתי אתאבותיכם במדבר ארץ מצרים כן אשפט אתכם נאם אדני יהוה",
      "header": "",
      "footer": ""
    },
    {
      "book_name": "Ezekiel",
      "chapter": 20,
      "verse": 37,
      "text": "והעברתי אתכם תחת השבט והבאתי אתכם במסרת הברית",
      "header": "",
      "footer": ""
    },
    {
      "book_name": "Ezekiel",
      "chapter": 20,
      "verse": 38,
      "text": "וברותי מכם המרדים והפושעים בי מארץ מגוריהם אוציא אותם ואלאדמת ישראל לא יבוא וידעתם כיאני יהוה",
      "header": "",
      "footer": ""
    },
    {
      "book_name": "Ezekiel",
      "chapter": 20,
      "verse": 39,
      "text": "ואתם ביתישראל כהאמר אדני יהוה איש גלוליו לכו עבדו ואחר אםאינכם שמעים אלי ואתשם קדשי לא תחללועוד במתנותיכם ובגלוליכם",
      "header": "",
      "footer": ""
    },
    {
      "book_name": "Ezekiel",
      "chapter": 20,
      "verse": 40,
      "text": "כי בהרקדשי בהר מרום ישראל נאם אדני יהוה שם יעבדני כלבית ישראל כלה בארץ שם ארצם ושם אדרוש אתתרומתיכם ואתראשית משאותיכם בכלקדשיכם",
      "header": "",
      "footer": ""
    },
    {
      "book_name": "Ezekiel",
      "chapter": 20,
      "verse": 41,
      "text": "בריח ניחח ארצה אתכם בהוציאי אתכם מןהעמים וקבצתי אתכם מןהארצות אשר נפצתם בם ונקדשתי בכם לעיני הגוים",
      "header": "",
      "footer": ""
    },
    {
      "book_name": "Ezekiel",
      "chapter": 20,
      "verse": 42,
      "text": "וידעתם כיאני יהוה בהביאי אתכם אלאדמת ישראל אלהארץ אשר נשאתי אתידי לתת אותה לאבותיכם",
      "header": "",
      "footer": ""
    },
    {
      "book_name": "Ezekiel",
      "chapter": 20,
      "verse": 43,
      "text": "וזכרתםשם אתדרכיכם ואת כלעלילותיכם אשר נטמאתם בם ונקטתם בפניכם בכלרעותיכם אשר עשיתם",
      "header": "",
      "footer": ""
    },
    {
      "book_name": "Ezekiel",
      "chapter": 20,
      "verse": 44,
      "text": "וידעתם כיאני יהוה בעשותי אתכם למען שמי לא כדרכיכם הרעים וכעלילותיכם הנשחתות בית ישראל נאם אדני יהוה פ",
      "header": "",
      "footer": ""
    },
    {
      "book_name": "Ezekiel",
      "chapter": 20,
      "verse": 45,
      "text": "ויהי דבריהוה אלי לאמר",
      "header": "",
      "footer": ""
    },
    {
      "book_name": "Ezekiel",
      "chapter": 20,
      "verse": 46,
      "text": "בןאדם שים פניך דרך תימנה והטף אלדרום והנבא אליער השדה נגב",
      "header": "",
      "footer": ""
    },
    {
      "book_name": "Ezekiel",
      "chapter": 20,
      "verse": 47,
      "text": "ואמרת ליער הנגב שמע דבריהוה כהאמר אדני יהוה הנני מציתבך אש ואכלה בך כלעץלח וכלעץ יבש לאתכבה להבת שלהבת ונצרבובה כלפנים מנגב צפונה",
      "header": "",
      "footer": ""
    },
    {
      "book_name": "Ezekiel",
      "chapter": 20,
      "verse": 48,
      "text": "וראו כלבשר כי אני יהוה בערתיה לא תכבה",
      "header": "",
      "footer": ""
    },
    {
      "book_name": "Ezekiel",
      "chapter": 20,
      "verse": 49,
      "text": "ואמר אהה אדני יהוה המה אמרים לי הלא ממשל משלים הוא פ",
      "header": "",
      "footer": ""
    }
  ]
}