{
  "book_name": "Job",
  "chapter": 37,
  "verses": [
    {
      "book_name": "Job",
      "chapter": 37,
      "verse": 1,
      "text": "אףלזאת יחרד לבי ויתר ממקומו",
      "header": "",
      "footer": ""
    },
    {
      "book_name": "Job",
      "chapter": 37,
      "verse": 2,
      "text": "שמעו שמוע ברגז קלו והגה מפיו יצא",
      "header": "",
      "footer": ""
    },
    {
      "book_name": "Job",
      "chapter": 37,
      "verse": 3,
      "text": "תחתכלהשמים ישרהו ואורו עלכנפות הארץ",
      "header": "",
      "footer": ""
    },
    {
      "book_name": "Job",
      "chapter": 37,
      "verse": 4,
      "text": "אחריו ישאגקול ירעם בקול גאונו ולא יעקבם כיישמע קולו",
      "header": "",
      "footer": ""
    },
    {
      "book_name": "Job",
      "chapter": 37,
      "verse": 5,
      "text": "ירעם אל בקולו נפלאות עשה גדלות ולא נדע",
      "header": "",
      "footer": ""
    },
    {
      "book_name": "Job",
      "chapter": 37,
      "verse": 6,
      "text": "כי לשלג יאמר הוא ארץ וגשם מטר וגשם מטרות עזו",
      "header": "",
      "footer": ""
    },
    {
      "book_name": "Job",
      "chapter": 37,
      "verse": 7,
      "text": "בידכלאדם יחתום לדעת כלאנשי מעשהו",
      "header": "",
      "footer": ""
    },
    {
      "book_name": "Job",
      "chapter": 37,
      "verse": 8,
      "text": "ותבא חיה במוארב ובמעונתיה תשכן",
      "header": "",
      "footer": ""
    },
    {
      "book_name": "Job",
      "chapter": 37,
      "verse": 9,
      "text": "מןהחדר תבוא סופה וממזרים קרה",
      "header": "",
      "footer": ""
    },
    {
      "book_name": "Job",
      "chapter": 37,
      "verse": 10,
      "text": "מנשמתאל יתןקרח ורחב מים במוצק",
      "header": "",
      "footer": ""
    },
    {
      "book_name": "Job",
      "chapter": 37,
      "verse": 11,
      "text": "אףברי יטריח עב יפיץ ענן אורו",
      "header": "",
      "footer": ""
    },
    {
      "book_name": "Job",
      "chapter": 37,
      "verse": 12,
      "text": "והוא מסבות מתהפך בתחבולתו לפעלם כל אשר יצום עלפני תבל ארצה",
      "header": "",
      "footer": ""
    },
    {
      "book_name": "Job",
      "chapter": 37,
      "verse": 13,
      "text": "אםלשבט אםלארצו אםלחסד ימצאהו",
      "header": "",
      "footer": ""
    },
    {
      "book_name": "Job",
      "chapter": 37,
      "verse": 14,
      "text": "האזינה זאת איוב עמד והתבונן נפלאות אל",
      "header": "",
      "footer": ""
    },
    {
      "book_name": "Job",
      "chapter": 37,
      "verse": 15,
      "text": "התדע בשוםאלוה עליהם והופיע אור עננו",
      "header": "",
      "footer": ""
    },
    {
      "book_name": "Job",
      "chapter": 37,
      "verse": 16,
      "text": "התדע עלמפלשיעב מפלאות תמים דעים",
      "header": "",
      "footer": ""
    },
    {
      "book_name": "Job",
      "chapter": 37,
      "verse": 17,
      "text": "אשרבגדיך חמים בהשקט ארץ מדרום",
      "header": "",
      "footer": ""
    },
    {
      "book_name": "Job",
      "chapter": 37,
      "verse": 18,
      "text": "תרקיע עמו לשחקים חזקים כראי מוצק",
      "header": "",
      "footer": ""
    },
    {
      "book_name": "Job",
      "chapter": 37,
      "verse": 19,
      "text": "הודיענו מהנאמר לו לאנערך מפניחשך",
      "header": "",
      "footer": ""
    },
    {
      "book_name": "Job",
      "chapter": 37,
      "verse": 20,
      "text": "היספרלו כי אדבר אםאמר איש כי יבלע",
      "header": "",
      "footer": ""
    },
    {
      "book_name": "Job",
      "chapter": 37,
      "verse": 21,
      "text": "ועתה לא ראו אור בהיר הוא בשחקים ורוח עברה ותטהרם",
      "header": "",
      "footer": ""
    },
    {
      "book_name": "Job",
      "chapter": 37,
      "verse": 22,
      "text": "מצפון זהב יאתה עלאלוה נורא הוד",
      "header": "",
      "footer": ""
    },
    {
      "book_name": "Job",
      "chapter": 37,
      "verse": 23,
      "text": "שדי לאמצאנהו שגיאכח ומשפט ורבצדקה לא יענה",
      "header": "",
      "footer": ""
    },
    {
      "book_name": "Job",
      "chapter": 37,
      "verse": 24,
      "text": "לכן יראוהו אנשים לאיראה כלחכמילב פ",
      "header": "",
      "footer": ""
    }
  ]
}