{
  "book_name": "2 Chronicles",
  "chapter": 11,
  "verses": [
    {
      "book_name": "2 Chronicles",
      "chapter": 11,
      "verse": 1,
      "text": "ויבא רחבעם ירושלם ויקהל אתבית יהודה ובנימן מאה ושמונים אלף בחור עשה מלחמה להלחם עםישראל להשיב אתהממלכה לרחבעם פ",
      "header": "",
      "footer": ""
    },
    {
      "book_name": "2 Chronicles",
      "chapter": 11,
      "verse": 2,
      "text": "ויהי דבריהוה אלשמעיהו אישהאלהים לאמר",
      "header": "",
      "footer": ""
    },
    {
      "book_name": "2 Chronicles",
      "chapter": 11,
      "verse": 3,
      "text": "אמר אלרחבעם בןשלמה מלך יהודה ואל כלישראל ביהודה ובנימן לאמר",
      "header": "",
      "footer": ""
    },
    {
      "book_name": "2 Chronicles",
      "chapter": 11,
      "verse": 4,
      "text": "כה אמר יהוה לאתעלו ולאתלחמו עםאחיכם שובו איש לביתו כי מאתי נהיה הדבר הזה וישמעו אתדברי יהוה וישבו מלכת אלירבעם פ",
      "header": "",
      "footer": ""
    },
    {
      "book_name": "2 Chronicles",
      "chapter": 11,
      "verse": 5,
      "text": "וישב רחבעם בירושלם ויבן ערים למצור ביהודה",
      "header": "",
      "footer": ""
    },
    {
      "book_name": "2 Chronicles",
      "chapter": 11,
      "verse": 6,
      "text": "ויבן אתביתלחם ואתעיטם ואתתקוע",
      "header": "",
      "footer": ""
    },
    {
      "book_name": "2 Chronicles",
      "chapter": 11,
      "verse": 7,
      "text": "ואתביתצור ואתשוכו ואתעדלם",
      "header": "",
      "footer": ""
    },
    {
      "book_name": "2 Chronicles",
      "chapter": 11,
      "verse": 8,
      "text": "ואתגת ואתמרשה ואתזיף",
      "header": "",
      "footer": ""
    },
    {
      "book_name": "2 Chronicles",
      "chapter": 11,
      "verse": 9,
      "text": "ואתאדורים ואתלכיש ואתעזקה",
      "header": "",
      "footer": ""
    },
    {
      "book_name": "2 Chronicles",
      "chapter": 11,
      "verse": 10,
      "text": "ואתצרעה ואתאילון ואתחברון אשר ביהודה ובבנימן ערי מצרות",
      "header": "",
      "footer": ""
    },
    {
      "book_name": "2 Chronicles",
      "chapter": 11,
      "verse": 11,
      "text": "ויחזק אתהמצרות ויתן בהם נגידים ואצרות מאכל ושמן ויין",
      "header": "",
      "footer": ""
    },
    {
      "book_name": "2 Chronicles",
      "chapter": 11,
      "verse": 12,
      "text": "ובכלעיר ועיר צנות ורמחים ויחזקם להרבה מאד ויהילו יהודה ובנימן ס",
      "header": "",
      "footer": ""
    },
    {
      "book_name": "2 Chronicles",
      "chapter": 11,
      "verse": 13,
      "text": "והכהנים והלוים אשר בכלישראל התיצבו עליו מכלגבולם",
      "header": "",
      "footer": ""
    },
    {
      "book_name": "2 Chronicles",
      "chapter": 11,
      "verse": 14,
      "text": "כיעזבו הלוים אתמגרשיהם ואחזתם וילכו ליהודה ולירושלם כיהזניחם ירבעם ובניו מכהן ליהוה",
      "header": "",
      "footer": ""
    },
    {
      "book_name": "2 Chronicles",
      "chapter": 11,
      "verse": 15,
      "text": "ויעמדלו כהנים לבמות ולשעירים ולעגלים אשר עשה",
      "header": "",
      "footer": ""
    },
    {
      "book_name": "2 Chronicles",
      "chapter": 11,
      "verse": 16,
      "text": "ואחריהם מכל שבטי ישראל הנתנים אתלבבם לבקש אתיהוה אלהי ישראל באו ירושלם לזבוח ליהוה אלהי אבותיהם",
      "header": "",
      "footer": ""
    },
    {
      "book_name": "2 Chronicles",
      "chapter": 11,
      "verse": 17,
      "text": "ויחזקו אתמלכות יהודה ויאמצו אתרחבעם בןשלמה לשנים שלוש כי הלכו בדרך דויד ושלמה לשנים שלוש",
      "header": "",
      "footer": ""
    },
    {
      "book_name": "2 Chronicles",
      "chapter": 11,
      "verse": 18,
      "text": "ויקחלו רחבעם אשה אתמחלת בןירימות בןדויד אביהיל בתאליאב בןישי",
      "header": "",
      "footer": ""
    },
    {
      "book_name": "2 Chronicles",
      "chapter": 11,
      "verse": 19,
      "text": "ותלד לו בנים אתיעוש ואתשמריה ואתזהם",
      "header": "",
      "footer": ""
    },
    {
      "book_name": "2 Chronicles",
      "chapter": 11,
      "verse": 20,
      "text": "ואחריה לקח אתמעכה בתאבשלום ותלד לו אתאביה ואתעתי ואתזיזא ואתשלמית",
      "header": "",
      "footer": ""
    },
    {
      "book_name": "2 Chronicles",
      "chapter": 11,
      "verse": 21,
      "text": "ויאהב רחבעם אתמעכה בתאבשלום מכלנשיו ופילגשיו כי נשים שמונהעשרה נשא ופילגשים ששים ויולד עשרים ושמונה בנים וששים בנות",
      "header": "",
      "footer": ""
    },
    {
      "book_name": "2 Chronicles",
      "chapter": 11,
      "verse": 22,
      "text": "ויעמד לראש רחבעם אתאביה בןמעכה לנגיד באחיו כי להמליכו",
      "header": "",
      "footer": ""
    },
    {
      "book_name": "2 Chronicles",
      "chapter": 11,
      "verse": 23,
      "text": "ויבן ויפרץ מכלבניו לכלארצות יהודה ובנימן לכל ערי המצרות ויתן להם המזון לרב וישאל המון נשים",
      "header": "",
      "footer": ""
    }
  ]
}