{
  "book_name": "Exodus",
  "chapter": 39,
  "verses": [
    {
      "book_name": "Exodus",
      "chapter": 39,
      "verse": 1,
      "text": "ומןהתכלת והארגמן ותולעת השני עשו בגדישרד לשרת בקדש ויעשו אתבגדי הקדש אשר לאהרן כאשר צוה יהוה אתמשה פ",
      "header": "",
      "footer": ""
    },
    {
      "book_name": "Exodus",
      "chapter": 39,
      "verse": 2,
      "text": "ויעש אתהאפד זהב תכלת וארגמן ותולעת שני ושש משזר",
      "header": "",
      "footer": ""
    },
    {
      "book_name": "Exodus",
      "chapter": 39,
      "verse": 3,
      "text": "וירקעו אתפחי הזהב וקצץ פתילם לעשות בתוך התכלת ובתוך הארגמן ובתוך תולעת השני ובתוך השש מעשה חשב",
      "header": "",
      "footer": ""
    },
    {
      "book_name": "Exodus",
      "chapter": 39,
      "verse": 4,
      "text": "כתפת עשולו חברת עלשני קצוותו חבר",
      "header": "",
      "footer": ""
    },
    {
      "book_name": "Exodus",
      "chapter": 39,
      "verse": 5,
      "text": "וחשב אפדתו אשר עליו ממנו הוא כמעשהו זהב תכלת וארגמן ותולעת שני ושש משזר כאשר צוה יהוה אתמשה",
      "header": "",
      "footer": ""
    },
    {
      "book_name": "Exodus",
      "chapter": 39,
      "verse": 6,
      "text": "ויעשו אתאבני השהם מסבת משבצת זהב מפתחת פתוחי חותם עלשמות בני ישראל",
      "header": "",
      "footer": ""
    },
    {
      "book_name": "Exodus",
      "chapter": 39,
      "verse": 7,
      "text": "וישם אתם על כתפת האפד אבני זכרון לבני ישראל כאשר צוה יהוה אתמשה פ",
      "header": "",
      "footer": ""
    },
    {
      "book_name": "Exodus",
      "chapter": 39,
      "verse": 8,
      "text": "ויעש אתהחשן מעשה חשב כמעשה אפד זהב תכלת וארגמן ותולעת שני ושש משזר",
      "header": "",
      "footer": ""
    },
    {
      "book_name": "Exodus",
      "chapter": 39,
      "verse": 9,
      "text": "רבוע היה כפול עשו אתהחשן זרת ארכו וזרת רחבו כפול",
      "header": "",
      "footer": ""
    },
    {
      "book_name": "Exodus",
      "chapter": 39,
      "verse": 10,
      "text": "וימלאובו ארבעה טורי אבן טור אדם פטדה וברקת הטור האחד",
      "header": "",
      "footer": ""
    },
    {
      "book_name": "Exodus",
      "chapter": 39,
      "verse": 11,
      "text": "והטור השני נפך ספיר ויהלם",
      "header": "",
      "footer": ""
    },
    {
      "book_name": "Exodus",
      "chapter": 39,
      "verse": 12,
      "text": "והטור השלישי לשם שבו ואחלמה",
      "header": "",
      "footer": ""
    },
    {
      "book_name": "Exodus",
      "chapter": 39,
      "verse": 13,
      "text": "והטור הרביעי תרשיש שהם וישפה מוסבת משבצות זהב במלאתם",
      "header": "",
      "footer": ""
    },
    {
      "book_name": "Exodus",
      "chapter": 39,
      "verse": 14,
      "text": "והאבנים עלשמת בניישראל הנה שתים עשרה עלשמתם פתוחי חתם איש עלשמו לשנים עשר שבט",
      "header": "",
      "footer": ""
    },
    {
      "book_name": "Exodus",
      "chapter": 39,
      "verse": 15,
      "text": "ויעשו עלהחשן שרשרת גבלת מעשה עבת זהב טהור",
      "header": "",
      "footer": ""
    },
    {
      "book_name": "Exodus",
      "chapter": 39,
      "verse": 16,
      "text": "ויעשו שתי משבצת זהב ושתי טבעת זהב ויתנו אתשתי הטבעת עלשני קצות החשן",
      "header": "",
      "footer": ""
    },
    {
      "book_name": "Exodus",
      "chapter": 39,
      "verse": 17,
      "text": "ויתנו שתי העבתת הזהב עלשתי הטבעת עלקצות החשן",
      "header": "",
      "footer": ""
    },
    {
      "book_name": "Exodus",
      "chapter": 39,
      "verse": 18,
      "text": "ואת שתי קצות שתי העבתת נתנו עלשתי המשבצת ויתנם עלכתפת האפד אלמול פניו",
      "header": "",
      "footer": ""
    },
    {
      "book_name": "Exodus",
      "chapter": 39,
      "verse": 19,
      "text": "ויעשו שתי טבעת זהב וישימו עלשני קצות החשן עלשפתו אשר אלעבר האפד ביתה",
      "header": "",
      "footer": ""
    },
    {
      "book_name": "Exodus",
      "chapter": 39,
      "verse": 20,
      "text": "ויעשו שתי טבעת זהב ויתנם עלשתי כתפת האפד מלמטה ממול פניו לעמת מחברתו ממעל לחשב האפד",
      "header": "",
      "footer": ""
    },
    {
      "book_name": "Exodus",
      "chapter": 39,
      "verse": 21,
      "text": "וירכסו אתהחשן מטבעתיו אלטבעת האפד בפתיל תכלת להית עלחשב האפד ולאיזח החשן מעל האפד כאשר צוה יהוה אתמשה",
      "header": "",
      "footer": ""
    },
    {
      "book_name": "Exodus",
      "chapter": 39,
      "verse": 22,
      "text": "ויעש אתמעיל האפד מעשה ארג כליל תכלת",
      "header": "",
      "footer": ""
    },
    {
      "book_name": "Exodus",
      "chapter": 39,
      "verse": 23,
      "text": "ופיהמעיל בתוכו כפי תחרא שפה לפיו סביב לא יקרע",
      "header": "",
      "footer": ""
    },
    {
      "book_name": "Exodus",
      "chapter": 39,
      "verse": 24,
      "text": "ויעשו עלשולי המעיל רמוני תכלת וארגמן ותולעת שני משזר",
      "header": "",
      "footer": ""
    },
    {
      "book_name": "Exodus",
      "chapter": 39,
      "verse": 25,
      "text": "ויעשו פעמני זהב טהור ויתנו אתהפעמנים בתוך הרמנים עלשולי המעיל סביב בתוך הרמנים",
      "header": "",
      "footer": ""
    },
    {
      "book_name": "Exodus",
      "chapter": 39,
      "verse": 26,
      "text": "פעמן ורמן פעמן ורמן עלשולי המעיל סביב לשרת כאשר צוה יהוה אתמשה ס",
      "header": "",
      "footer": ""
    },
    {
      "book_name": "Exodus",
      "chapter": 39,
      "verse": 27,
      "text": "ויעשו אתהכתנת שש מעשה ארג לאהרן ולבניו",
      "header": "",
      "footer": ""
    },
    {
      "book_name": "Exodus",
      "chapter": 39,
      "verse": 28,
      "text": "ואת המצנפת שש ואתפארי המגבעת שש ואתמכנסי הבד שש משזר",
      "header": "",
      "footer": ""
    },
    {
      "book_name": "Exodus",
      "chapter": 39,
      "verse": 29,
      "text": "ואתהאבנט שש משזר ותכלת וארגמן ותולעת שני מעשה רקם כאשר צוה יהוה אתמשה ס",
      "header": "",
      "footer": ""
    },
    {
      "book_name": "Exodus",
      "chapter": 39,
      "verse": 30,
      "text": "ויעשו אתציץ נזרהקדש זהב טהור ויכתבו עליו מכתב פתוחי חותם קדש ליהוה",
      "header": "",
      "footer": ""
    },
    {
      "book_name": "Exodus",
      "chapter": 39,
      "verse": 31,
      "text": "ויתנו עליו פתיל תכלת לתת עלהמצנפת מלמעלה כאשר צוה יהוה אתמשה ס",
      "header": "",
      "footer": ""
    },
    {
      "book_name": "Exodus",
      "chapter": 39,
      "verse": 32,
      "text": "ותכל כלעבדת משכן אהל מועד ויעשו בני ישראל ככל אשר צוה יהוה אתמשה כן עשו פ",
      "header": "",
      "footer": ""
    },
    {
      "book_name": "Exodus",
      "chapter": 39,
      "verse": 33,
      "text": "ויביאו אתהמשכן אלמשה אתהאהל ואתכלכליו קרסיו קרשיו בריחו ועמדיו ואדניו",
      "header": "",
      "footer": ""
    },
    {
      "book_name": "Exodus",
      "chapter": 39,
      "verse": 34,
      "text": "ואתמכסה עורת האילם המאדמים ואתמכסה ערת התחשים ואת פרכת המסך",
      "header": "",
      "footer": ""
    },
    {
      "book_name": "Exodus",
      "chapter": 39,
      "verse": 35,
      "text": "אתארן העדת ואתבדיו ואת הכפרת",
      "header": "",
      "footer": ""
    },
    {
      "book_name": "Exodus",
      "chapter": 39,
      "verse": 36,
      "text": "אתהשלחן אתכלכליו ואת לחם הפנים",
      "header": "",
      "footer": ""
    },
    {
      "book_name": "Exodus",
      "chapter": 39,
      "verse": 37,
      "text": "אתהמנרה הטהרה אתנרתיה נרת המערכה ואתכלכליה ואת שמן המאור",
      "header": "",
      "footer": ""
    },
    {
      "book_name": "Exodus",
      "chapter": 39,
      "verse": 38,
      "text": "ואת מזבח הזהב ואת שמן המשחה ואת קטרת הסמים ואת מסך פתח האהל",
      "header": "",
      "footer": ""
    },
    {
      "book_name": "Exodus",
      "chapter": 39,
      "verse": 39,
      "text": "את מזבח הנחשת ואתמכבר הנחשת אשרלו אתבדיו ואתכלכליו אתהכיר ואתכנו",
      "header": "",
      "footer": ""
    },
    {
      "book_name": "Exodus",
      "chapter": 39,
      "verse": 40,
      "text": "את קלעי החצר אתעמדיה ואתאדניה ואתהמסך לשער החצר אתמיתריו ויתדתיה ואת כלכלי עבדת המשכן לאהל מועד",
      "header": "",
      "footer": ""
    },
    {
      "book_name": "Exodus",
      "chapter": 39,
      "verse": 41,
      "text": "אתבגדי השרד לשרת בקדש אתבגדי הקדש לאהרן הכהן ואתבגדי בניו לכהן",
      "header": "",
      "footer": ""
    },
    {
      "book_name": "Exodus",
      "chapter": 39,
      "verse": 42,
      "text": "ככל אשרצוה יהוה אתמשה כן עשו בני ישראל את כלהעבדה",
      "header": "",
      "footer": ""
    },
    {
      "book_name": "Exodus",
      "chapter": 39,
      "verse": 43,
      "text": "וירא משה אתכלהמלאכה והנה עשו אתה כאשר צוה יהוה כן עשו ויברך אתם משה פ",
      "header": "",
      "footer": ""
    }
  ]
}