{
  "book_name": "Ecclesiastes",
  "chapter": 1,
  "verses": [
    {
      "book_name": "Ecclesiastes",
      "chapter": 1,
      "verse": 1,
      "text": "דברי קהלת בןדוד מלך בירושלם",
      "header": "",
      "footer": ""
    },
    {
      "book_name": "Ecclesiastes",
      "chapter": 1,
      "verse": 2,
      "text": "הבל הבלים אמר קהלת הבל הבלים הכל הבל",
      "header": "",
      "footer": ""
    },
    {
      "book_name": "Ecclesiastes",
      "chapter": 1,
      "verse": 3,
      "text": "מהיתרון לאדם בכלעמלו שיעמל תחת השמש",
      "header": "",
      "footer": ""
    },
    {
      "book_name": "Ecclesiastes",
      "chapter": 1,
      "verse": 4,
      "text": "דור הלך ודור בא והארץ לעולם עמדת",
      "header": "",
      "footer": ""
    },
    {
      "book_name": "Ecclesiastes",
      "chapter": 1,
      "verse": 5,
      "text": "וזרח השמש ובא השמש ואלמקומו שואף זורח הוא שם",
      "header": "",
      "footer": ""
    },
    {
      "book_name": "Ecclesiastes",
      "chapter": 1,
      "verse": 6,
      "text": "הולך אלדרום וסובב אלצפון סובב סבב הולך הרוח ועלסביבתיו שב הרוח",
      "header": "",
      "footer": ""
    },
    {
      "book_name": "Ecclesiastes",
      "chapter": 1,
      "verse": 7,
      "text": "כלהנחלים הלכים אלהים והים איננו מלא אלמקום שהנחלים הלכים שם הם שבים ללכת",
      "header": "",
      "footer": ""
    },
    {
      "book_name": "Ecclesiastes",
      "chapter": 1,
      "verse": 8,
      "text": "כלהדברים יגעים לאיוכל איש לדבר לאתשבע עין לראות ולאתמלא אזן משמע",
      "header": "",
      "footer": ""
    },
    {
      "book_name": "Ecclesiastes",
      "chapter": 1,
      "verse": 9,
      "text": "מהשהיה הוא שיהיה ומהשנעשה הוא שיעשה ואין כלחדש תחת השמש",
      "header": "",
      "footer": ""
    },
    {
      "book_name": "Ecclesiastes",
      "chapter": 1,
      "verse": 10,
      "text": "יש דבר שיאמר ראהזה חדש הוא כבר היה לעלמים אשר היה מלפננו",
      "header": "",
      "footer": ""
    },
    {
      "book_name": "Ecclesiastes",
      "chapter": 1,
      "verse": 11,
      "text": "אין זכרון לראשנים וגם לאחרנים שיהיו לאיהיה להם זכרון עם שיהיו לאחרנה פ",
      "header": "",
      "footer": ""
    },
    {
      "book_name": "Ecclesiastes",
      "chapter": 1,
      "verse": 12,
      "text": "אני קהלת הייתי מלך עלישראל בירושלם",
      "header": "",
      "footer": ""
    },
    {
      "book_name": "Ecclesiastes",
      "chapter": 1,
      "verse": 13,
      "text": "ונתתי אתלבי לדרוש ולתור בחכמה על כלאשר נעשה תחת השמים הוא ענין רע נתן אלהים לבני האדם לענות בו",
      "header": "",
      "footer": ""
    },
    {
      "book_name": "Ecclesiastes",
      "chapter": 1,
      "verse": 14,
      "text": "ראיתי אתכלהמעשים שנעשו תחת השמש והנה הכל הבל ורעות רוח",
      "header": "",
      "footer": ""
    },
    {
      "book_name": "Ecclesiastes",
      "chapter": 1,
      "verse": 15,
      "text": "מעות לאיוכל לתקן וחסרון לאיוכל להמנות",
      "header": "",
      "footer": ""
    },
    {
      "book_name": "Ecclesiastes",
      "chapter": 1,
      "verse": 16,
      "text": "דברתי אני עםלבי לאמר אני הנה הגדלתי והוספתי חכמה על כלאשרהיה לפני עלירושלם ולבי ראה הרבה חכמה ודעת",
      "header": "",
      "footer": ""
    },
    {
      "book_name": "Ecclesiastes",
      "chapter": 1,
      "verse": 17,
      "text": "ואתנה לבי לדעת חכמה ודעת הוללות ושכלות ידעתי שגםזה הוא רעיון רוח",
      "header": "",
      "footer": ""
    },
    {
      "book_name": "Ecclesiastes",
      "chapter": 1,
      "verse": 18,
      "text": "כי ברב חכמה רבכעס ויוסיף דעת יוסיף מכאוב",
      "header": "",
      "footer": ""
    }
  ]
}