{
  "book_name": "Numbers",
  "chapter": 1,
  "verses": [
    {
      "book_name": "Numbers",
      "chapter": 1,
      "verse": 1,
      "text": "וידבר יהוה אלמשה במדבר סיני באהל מועד באחד לחדש השני בשנה השנית לצאתם מארץ מצרים לאמר",
      "header": "",
      "footer": ""
    },
    {
      "book_name": "Numbers",
      "chapter": 1,
      "verse": 2,
      "text": "שאו אתראש כלעדת בניישראל למשפחתם לבית אבתם במספר שמות כלזכר לגלגלתם",
      "header": "",
      "footer": ""
    },
    {
      "book_name": "Numbers",
      "chapter": 1,
      "verse": 3,
      "text": "מבן עשרים שנה ומעלה כליצא צבא בישראל תפקדו אתם לצבאתם אתה ואהרן",
      "header": "",
      "footer": ""
    },
    {
      "book_name": "Numbers",
      "chapter": 1,
      "verse": 4,
      "text": "ואתכם יהיו איש איש למטה איש ראש לביתאבתיו הוא",
      "header": "",
      "footer": ""
    },
    {
      "book_name": "Numbers",
      "chapter": 1,
      "verse": 5,
      "text": "ואלה שמות האנשים אשר יעמדו אתכם לראובן אליצור בןשדיאור",
      "header": "",
      "footer": ""
    },
    {
      "book_name": "Numbers",
      "chapter": 1,
      "verse": 6,
      "text": "לשמעון שלמיאל בןצורישדי",
      "header": "",
      "footer": ""
    },
    {
      "book_name": "Numbers",
      "chapter": 1,
      "verse": 7,
      "text": "ליהודה נחשון בןעמינדב",
      "header": "",
      "footer": ""
    },
    {
      "book_name": "Numbers",
      "chapter": 1,
      "verse": 8,
      "text": "ליששכר נתנאל בןצוער",
      "header": "",
      "footer": ""
    },
    {
      "book_name": "Numbers",
      "chapter": 1,
      "verse": 9,
      "text": "לזבולן אליאב בןחלן",
      "header": "",
      "footer": ""
    },
    {
      "book_name": "Numbers",
      "chapter": 1,
      "verse": 10,
      "text": "לבני יוסף לאפרים אלישמע בןעמיהוד למנשה גמליאל בןפדהצור",
      "header": "",
      "footer": ""
    },
    {
      "book_name": "Numbers",
      "chapter": 1,
      "verse": 11,
      "text": "לבנימן אבידן בןגדעני",
      "header": "",
      "footer": ""
    },
    {
      "book_name": "Numbers",
      "chapter": 1,
      "verse": 12,
      "text": "לדן אחיעזר בןעמישדי",
      "header": "",
      "footer": ""
    },
    {
      "book_name": "Numbers",
      "chapter": 1,
      "verse": 13,
      "text": "לאשר פגעיאל בןעכרן",
      "header": "",
      "footer": ""
    },
    {
      "book_name": "Numbers",
      "chapter": 1,
      "verse": 14,
      "text": "לגד אליסף בןדעואל",
      "header": "",
      "footer": ""
    },
    {
      "book_name": "Numbers",
      "chapter": 1,
      "verse": 15,
      "text": "לנפתלי אחירע בןעינן",
      "header": "",
      "footer": ""
    },
    {
      "book_name": "Numbers",
      "chapter": 1,
      "verse": 16,
      "text": "אלה קריאי העדה נשיאי מטות אבותם ראשי אלפי ישראל הם",
      "header": "",
      "footer": ""
    },
    {
      "book_name": "Numbers",
      "chapter": 1,
      "verse": 17,
      "text": "ויקח משה ואהרן את האנשים האלה אשר נקבו בשמות",
      "header": "",
      "footer": ""
    },
    {
      "book_name": "Numbers",
      "chapter": 1,
      "verse": 18,
      "text": "ואת כלהעדה הקהילו באחד לחדש השני ויתילדו עלמשפחתם לבית אבתם במספר שמות מבן עשרים שנה ומעלה לגלגלתם",
      "header": "",
      "footer": ""
    },
    {
      "book_name": "Numbers",
      "chapter": 1,
      "verse": 19,
      "text": "כאשר צוה יהוה אתמשה ויפקדם במדבר סיני פ",
      "header": "",
      "footer": ""
    },
    {
      "book_name": "Numbers",
      "chapter": 1,
      "verse": 20,
      "text": "ויהיו בניראובן בכר ישראל תולדתם למשפחתם לבית אבתם במספר שמות לגלגלתם כלזכר מבן עשרים שנה ומעלה כל יצא צבא",
      "header": "",
      "footer": ""
    },
    {
      "book_name": "Numbers",
      "chapter": 1,
      "verse": 21,
      "text": "פקדיהם למטה ראובן ששה וארבעים אלף וחמש מאות פ",
      "header": "",
      "footer": ""
    },
    {
      "book_name": "Numbers",
      "chapter": 1,
      "verse": 22,
      "text": "לבני שמעון תולדתם למשפחתם לבית אבתם פקדיו במספר שמות לגלגלתם כלזכר מבן עשרים שנה ומעלה כל יצא צבא",
      "header": "",
      "footer": ""
    },
    {
      "book_name": "Numbers",
      "chapter": 1,
      "verse": 23,
      "text": "פקדיהם למטה שמעון תשעה וחמשים אלף ושלש מאות פ",
      "header": "",
      "footer": ""
    },
    {
      "book_name": "Numbers",
      "chapter": 1,
      "verse": 24,
      "text": "לבני גד תולדתם למשפחתם לבית אבתם במספר שמות מבן עשרים שנה ומעלה כל יצא צבא",
      "header": "",
      "footer": ""
    },
    {
      "book_name": "Numbers",
      "chapter": 1,
      "verse": 25,
      "text": "פקדיהם למטה גד חמשה וארבעים אלף ושש מאות וחמשים פ",
      "header": "",
      "footer": ""
    },
    {
      "book_name": "Numbers",
      "chapter": 1,
      "verse": 26,
      "text": "לבני יהודה תולדתם למשפחתם לבית אבתם במספר שמת מבן עשרים שנה ומעלה כל יצא צבא",
      "header": "",
      "footer": ""
    },
    {
      "book_name": "Numbers",
      "chapter": 1,
      "verse": 27,
      "text": "פקדיהם למטה יהודה ארבעה ושבעים אלף ושש מאות פ",
      "header": "",
      "footer": ""
    },
    {
      "book_name": "Numbers",
      "chapter": 1,
      "verse": 28,
      "text": "לבני יששכר תולדתם למשפחתם לבית אבתם במספר שמת מבן עשרים שנה ומעלה כל יצא צבא",
      "header": "",
      "footer": ""
    },
    {
      "book_name": "Numbers",
      "chapter": 1,
      "verse": 29,
      "text": "פקדיהם למטה יששכר ארבעה וחמשים אלף וארבע מאות פ",
      "header": "",
      "footer": ""
    },
    {
      "book_name": "Numbers",
      "chapter": 1,
      "verse": 30,
      "text": "לבני זבולן תולדתם למשפחתם לבית אבתם במספר שמת מבן עשרים שנה ומעלה כל יצא צבא",
      "header": "",
      "footer": ""
    },
    {
      "book_name": "Numbers",
      "chapter": 1,
      "verse": 31,
      "text": "פקדיהם למטה זבולן שבעה וחמשים אלף וארבע מאות פ",
      "header": "",
      "footer": ""
    },
    {
      "book_name": "Numbers",
      "chapter": 1,
      "verse": 32,
      "text": "לבני יוסף לבני אפרים תולדתם למשפחתם לבית אבתם במספר שמת מבן עשרים שנה ומעלה כל יצא צבא",
      "header": "",
      "footer": ""
    },
    {
      "book_name": "Numbers",
      "chapter": 1,
      "verse": 33,
      "text": "פקדיהם למטה אפרים ארבעים אלף וחמש מאות פ",
      "header": "",
      "footer": ""
    },
    {
      "book_name": "Numbers",
      "chapter": 1,
      "verse": 34,
      "text": "לבני מנשה תולדתם למשפחתם לבית אבתם במספר שמות מבן עשרים שנה ומעלה כל יצא צבא",
      "header": "",
      "footer": ""
    },
    {
      "book_name": "Numbers",
      "chapter": 1,
      "verse": 35,
      "text": "פקדיהם למטה מנשה שנים ושלשים אלף ומאתים פ",
      "header": "",
      "footer": ""
    },
    {
      "book_name": "Numbers",
      "chapter": 1,
      "verse": 36,
      "text": "לבני בנימן תולדתם למשפחתם לבית אבתם במספר שמת מבן עשרים שנה ומעלה כל יצא צבא",
      "header": "",
      "footer": ""
    },
    {
      "book_name": "Numbers",
      "chapter": 1,
      "verse": 37,
      "text": "פקדיהם למטה בנימן חמשה ושלשים אלף וארבע מאות פ",
      "header": "",
      "footer": ""
    },
    {
      "book_name": "Numbers",
      "chapter": 1,
      "verse": 38,
      "text": "לבני דן תולדתם למשפחתם לבית אבתם במספר שמת מבן עשרים שנה ומעלה כל יצא צבא",
      "header": "",
      "footer": ""
    },
    {
      "book_name": "Numbers",
      "chapter": 1,
      "verse": 39,
      "text": "פקדיהם למטה דן שנים וששים אלף ושבע מאות פ",
      "header": "",
      "footer": ""
    },
    {
      "book_name": "Numbers",
      "chapter": 1,
      "verse": 40,
      "text": "לבני אשר תולדתם למשפחתם לבית אבתם במספר שמת מבן עשרים שנה ומעלה כל יצא צבא",
      "header": "",
      "footer": ""
    },
    {
      "book_name": "Numbers",
      "chapter": 1,
      "verse": 41,
      "text": "פקדיהם למטה אשר אחד וארבעים אלף וחמש מאות פ",
      "header": "",
      "footer": ""
    },
    {
      "book_name": "Numbers",
      "chapter": 1,
      "verse": 42,
      "text": "בני נפתלי תולדתם למשפחתם לבית אבתם במספר שמת מבן עשרים שנה ומעלה כל יצא צבא",
      "header": "",
      "footer": ""
    },
    {
      "book_name": "Numbers",
      "chapter": 1,
      "verse": 43,
      "text": "פקדיהם למטה נפתלי שלשה וחמשים אלף וארבע מאות פ",
      "header": "",
      "footer": ""
    },
    {
      "book_name": "Numbers",
      "chapter": 1,
      "verse": 44,
      "text": "אלה הפקדים אשר פקד משה ואהרן ונשיאי ישראל שנים עשר איש אישאחד לביתאבתיו היו",
      "header": "",
      "footer": ""
    },
    {
      "book_name": "Numbers",
      "chapter": 1,
      "verse": 45,
      "text": "ויהיו כלפקודי בניישראל לבית אבתם מבן עשרים שנה ומעלה כליצא צבא בישראל",
      "header": "",
      "footer": ""
    },
    {
      "book_name": "Numbers",
      "chapter": 1,
      "verse": 46,
      "text": "ויהיו כלהפקדים ששמאות אלף ושלשת אלפים וחמש מאות וחמשים",
      "header": "",
      "footer": ""
    },
    {
      "book_name": "Numbers",
      "chapter": 1,
      "verse": 47,
      "text": "והלוים למטה אבתם לא התפקדו בתוכם פ",
      "header": "",
      "footer": ""
    },
    {
      "book_name": "Numbers",
      "chapter": 1,
      "verse": 48,
      "text": "וידבר יהוה אלמשה לאמר",
      "header": "",
      "footer": ""
    },
    {
      "book_name": "Numbers",
      "chapter": 1,
      "verse": 49,
      "text": "אך אתמטה לוי לא תפקד ואתראשם לא תשא בתוך בני ישראל",
      "header": "",
      "footer": ""
    },
    {
      "book_name": "Numbers",
      "chapter": 1,
      "verse": 50,
      "text": "ואתה הפקד אתהלוים עלמשכן העדת ועל כלכליו ועל כלאשרלו המה ישאו אתהמשכן ואתכלכליו והם ישרתהו וסביב למשכן יחנו",
      "header": "",
      "footer": ""
    },
    {
      "book_name": "Numbers",
      "chapter": 1,
      "verse": 51,
      "text": "ובנסע המשכן יורידו אתו הלוים ובחנת המשכן יקימו אתו הלוים והזר הקרב יומת",
      "header": "",
      "footer": ""
    },
    {
      "book_name": "Numbers",
      "chapter": 1,
      "verse": 52,
      "text": "וחנו בני ישראל איש עלמחנהו ואיש עלדגלו לצבאתם",
      "header": "",
      "footer": ""
    },
    {
      "book_name": "Numbers",
      "chapter": 1,
      "verse": 53,
      "text": "והלוים יחנו סביב למשכן העדת ולאיהיה קצף עלעדת בני ישראל ושמרו הלוים אתמשמרת משכן העדות",
      "header": "",
      "footer": ""
    },
    {
      "book_name": "Numbers",
      "chapter": 1,
      "verse": 54,
      "text": "ויעשו בני ישראל ככל אשר צוה יהוה אתמשה כן עשו פ",
      "header": "",
      "footer": ""
    }
  ]
}