{
  "book_name": "1 Kings",
  "chapter": 10,
  "verses": [
    {
      "book_name": "1 Kings",
      "chapter": 10,
      "verse": 1,
      "text": "ומלכתשבא שמעת אתשמע שלמה לשם יהוה ותבא לנסתו בחידות",
      "header": "",
      "footer": ""
    },
    {
      "book_name": "1 Kings",
      "chapter": 10,
      "verse": 2,
      "text": "ותבא ירושלמה בחיל כבד מאד גמלים נשאים בשמים וזהב רבמאד ואבן יקרה ותבא אלשלמה ותדבר אליו את כלאשר היה עםלבבה",
      "header": "",
      "footer": ""
    },
    {
      "book_name": "1 Kings",
      "chapter": 10,
      "verse": 3,
      "text": "ויגדלה שלמה אתכלדבריה לאהיה דבר נעלם מןהמלך אשר לא הגיד לה",
      "header": "",
      "footer": ""
    },
    {
      "book_name": "1 Kings",
      "chapter": 10,
      "verse": 4,
      "text": "ותרא מלכתשבא את כלחכמת שלמה והבית אשר בנה",
      "header": "",
      "footer": ""
    },
    {
      "book_name": "1 Kings",
      "chapter": 10,
      "verse": 5,
      "text": "ומאכל שלחנו ומושב עבדיו ומעמד משרתו ומלבשיהם ומשקיו ועלתו אשר יעלה בית יהוה ולאהיה בה עוד רוח",
      "header": "",
      "footer": ""
    },
    {
      "book_name": "1 Kings",
      "chapter": 10,
      "verse": 6,
      "text": "ותאמר אלהמלך אמת היה הדבר אשר שמעתי בארצי עלדבריך ועלחכמתך",
      "header": "",
      "footer": ""
    },
    {
      "book_name": "1 Kings",
      "chapter": 10,
      "verse": 7,
      "text": "ולאהאמנתי לדברים עד אשרבאתי ותראינה עיני והנה לאהגדלי החצי הוספת חכמה וטוב אלהשמועה אשר שמעתי",
      "header": "",
      "footer": ""
    },
    {
      "book_name": "1 Kings",
      "chapter": 10,
      "verse": 8,
      "text": "אשרי אנשיך אשרי עבדיך אלה העמדים לפניך תמיד השמעים אתחכמתך",
      "header": "",
      "footer": ""
    },
    {
      "book_name": "1 Kings",
      "chapter": 10,
      "verse": 9,
      "text": "יהי יהוה אלהיך ברוך אשר חפץ בך לתתך עלכסא ישראל באהבת יהוה אתישראל לעלם וישימך למלך לעשות משפט וצדקה",
      "header": "",
      "footer": ""
    },
    {
      "book_name": "1 Kings",
      "chapter": 10,
      "verse": 10,
      "text": "ותתן למלך מאה ועשרים ככר זהב ובשמים הרבה מאד ואבן יקרה לאבא כבשם ההוא עוד לרב אשרנתנה מלכתשבא למלך שלמה",
      "header": "",
      "footer": ""
    },
    {
      "book_name": "1 Kings",
      "chapter": 10,
      "verse": 11,
      "text": "וגם אני חירם אשרנשא זהב מאופיר הביא מאפיר עצי אלמגים הרבה מאד ואבן יקרה",
      "header": "",
      "footer": ""
    },
    {
      "book_name": "1 Kings",
      "chapter": 10,
      "verse": 12,
      "text": "ויעש המלך אתעצי האלמגים מסעד לביתיהוה ולבית המלך וכנרות ונבלים לשרים לא באכן עצי אלמגים ולא נראה עד היום הזה",
      "header": "",
      "footer": ""
    },
    {
      "book_name": "1 Kings",
      "chapter": 10,
      "verse": 13,
      "text": "והמלך שלמה נתן למלכתשבא אתכלחפצה אשר שאלה מלבד אשר נתןלה כיד המלך שלמה ותפן ותלך לארצה היא ועבדיה ס",
      "header": "",
      "footer": ""
    },
    {
      "book_name": "1 Kings",
      "chapter": 10,
      "verse": 14,
      "text": "ויהי משקל הזהב אשרבא לשלמה בשנה אחת שש מאות ששים ושש ככר זהב",
      "header": "",
      "footer": ""
    },
    {
      "book_name": "1 Kings",
      "chapter": 10,
      "verse": 15,
      "text": "לבד מאנשי התרים ומסחר הרכלים וכלמלכי הערב ופחות הארץ",
      "header": "",
      "footer": ""
    },
    {
      "book_name": "1 Kings",
      "chapter": 10,
      "verse": 16,
      "text": "ויעש המלך שלמה מאתים צנה זהב שחוט ששמאות זהב יעלה עלהצנה האחת",
      "header": "",
      "footer": ""
    },
    {
      "book_name": "1 Kings",
      "chapter": 10,
      "verse": 17,
      "text": "ושלשמאות מגנים זהב שחוט שלשת מנים זהב יעלה עלהמגן האחת ויתנם המלך בית יער הלבנון פ",
      "header": "",
      "footer": ""
    },
    {
      "book_name": "1 Kings",
      "chapter": 10,
      "verse": 18,
      "text": "ויעש המלך כסאשן גדול ויצפהו זהב מופז",
      "header": "",
      "footer": ""
    },
    {
      "book_name": "1 Kings",
      "chapter": 10,
      "verse": 19,
      "text": "שש מעלות לכסה וראשעגל לכסה מאחריו וידת מזה ומזה אלמקום השבת ושנים אריות עמדים אצל הידות",
      "header": "",
      "footer": ""
    },
    {
      "book_name": "1 Kings",
      "chapter": 10,
      "verse": 20,
      "text": "ושנים עשר אריים עמדים שם עלשש המעלות מזה ומזה לאנעשה כן לכלממלכות",
      "header": "",
      "footer": ""
    },
    {
      "book_name": "1 Kings",
      "chapter": 10,
      "verse": 21,
      "text": "וכל כלי משקה המלך שלמה זהב וכל כלי ביתיער הלבנון זהב סגור אין כסף לא נחשב בימי שלמה למאומה",
      "header": "",
      "footer": ""
    },
    {
      "book_name": "1 Kings",
      "chapter": 10,
      "verse": 22,
      "text": "כי אני תרשיש למלך בים עם אני חירם אחת לשלש שנים תבוא אני תרשיש נשאת זהב וכסף שנהבים וקפים ותכיים",
      "header": "",
      "footer": ""
    },
    {
      "book_name": "1 Kings",
      "chapter": 10,
      "verse": 23,
      "text": "ויגדל המלך שלמה מכל מלכי הארץ לעשר ולחכמה",
      "header": "",
      "footer": ""
    },
    {
      "book_name": "1 Kings",
      "chapter": 10,
      "verse": 24,
      "text": "וכלהארץ מבקשים אתפני שלמה לשמע אתחכמתו אשרנתן אלהים בלבו",
      "header": "",
      "footer": ""
    },
    {
      "book_name": "1 Kings",
      "chapter": 10,
      "verse": 25,
      "text": "והמה מבאים איש מנחתו כלי כסף וכלי זהב ושלמות ונשק ובשמים סוסים ופרדים דברשנה בשנה ס",
      "header": "",
      "footer": ""
    },
    {
      "book_name": "1 Kings",
      "chapter": 10,
      "verse": 26,
      "text": "ויאסף שלמה רכב ופרשים ויהילו אלף וארבעמאות רכב ושניםעשר אלף פרשים וינחם בערי הרכב ועםהמלך בירושלם",
      "header": "",
      "footer": ""
    },
    {
      "book_name": "1 Kings",
      "chapter": 10,
      "verse": 27,
      "text": "ויתן המלך אתהכסף בירושלם כאבנים ואת הארזים נתן כשקמים אשרבשפלה לרב",
      "header": "",
      "footer": ""
    },
    {
      "book_name": "1 Kings",
      "chapter": 10,
      "verse": 28,
      "text": "ומוצא הסוסים אשר לשלמה ממצרים ומקוה סחרי המלך יקחו מקוה במחיר",
      "header": "",
      "footer": ""
    },
    {
      "book_name": "1 Kings",
      "chapter": 10,
      "verse": 29,
      "text": "ותעלה ותצא מרכבה ממצרים בשש מאות כסף וסוס בחמשים ומאה וכן לכלמלכי החתים ולמלכי ארם בידם יצאו פ",
      "header": "",
      "footer": ""
    }
  ]
}