{
  "book_name": "Jeremiah",
  "chapter": 24,
  "verses": [
    {
      "book_name": "Jeremiah",
      "chapter": 24,
      "verse": 1,
      "text": "הראני יהוה והנה שני דודאי תאנים מועדים לפני היכל יהוה אחרי הגלות נבוכדראצר מלךבבל אתיכניהו בןיהויקים מלךיהודה ואתשרי יהודה ואתהחרש ואתהמסגר מירושלם ויבאם בבל",
      "header": "",
      "footer": ""
    },
    {
      "book_name": "Jeremiah",
      "chapter": 24,
      "verse": 2,
      "text": "הדוד אחד תאנים טבות מאד כתאני הבכרות והדוד אחד תאנים רעות מאד אשר לאתאכלנה מרע ס",
      "header": "",
      "footer": ""
    },
    {
      "book_name": "Jeremiah",
      "chapter": 24,
      "verse": 3,
      "text": "ויאמר יהוה אלי מהאתה ראה ירמיהו ואמר תאנים התאנים הטבות טבות מאד והרעות רעות מאד אשר לאתאכלנה מרע פ",
      "header": "",
      "footer": ""
    },
    {
      "book_name": "Jeremiah",
      "chapter": 24,
      "verse": 4,
      "text": "ויהי דבריהוה אלי לאמר",
      "header": "",
      "footer": ""
    },
    {
      "book_name": "Jeremiah",
      "chapter": 24,
      "verse": 5,
      "text": "כהאמר יהוה אלהי ישראל כתאנים הטבות האלה כןאכיר אתגלות יהודה אשר שלחתי מןהמקום הזה ארץ כשדים לטובה",
      "header": "",
      "footer": ""
    },
    {
      "book_name": "Jeremiah",
      "chapter": 24,
      "verse": 6,
      "text": "ושמתי עיני עליהם לטובה והשבתים עלהארץ הזאת ובניתים ולא אהרס ונטעתים ולא אתוש",
      "header": "",
      "footer": ""
    },
    {
      "book_name": "Jeremiah",
      "chapter": 24,
      "verse": 7,
      "text": "ונתתי להם לב לדעת אתי כי אני יהוה והיולי לעם ואנכי אהיה להם לאלהים כיישבו אלי בכללבם ס",
      "header": "",
      "footer": ""
    },
    {
      "book_name": "Jeremiah",
      "chapter": 24,
      "verse": 8,
      "text": "וכתאנים הרעות אשר לאתאכלנה מרע כיכה אמר יהוה כן אתן אתצדקיהו מלךיהודה ואתשריו ואת שארית ירושלם הנשארים בארץ הזאת והישבים בארץ מצרים",
      "header": "",
      "footer": ""
    },
    {
      "book_name": "Jeremiah",
      "chapter": 24,
      "verse": 9,
      "text": "ונתתים לזועה לרעה לכל ממלכות הארץ לחרפה ולמשל לשנינה ולקללה בכלהמקמות אשראדיחם שם",
      "header": "",
      "footer": ""
    },
    {
      "book_name": "Jeremiah",
      "chapter": 24,
      "verse": 10,
      "text": "ושלחתי בם אתהחרב אתהרעב ואתהדבר עדתמם מעל האדמה אשרנתתי להם ולאבותיהם פ",
      "header": "",
      "footer": ""
    }
  ]
}